{
    "$schema": "https://json-schema.org/draft/2020-12/schema",
    "name": "Adventure Quest Design System",
    "version": "1.0.0",
    "description": "A playful, gamified design system for children's entrepreneurship education (BizKids AI). Designed for young CEOs aged 9-13 with a focus on engagement, approachability, and gamification.",
    "designPrinciples": {
        "summary": "Fun, friendly, and encouraging - every element should feel like an adventure",
        "principles": [
            {
                "name": "Playful & Inviting",
                "description": "Use bright, cheerful colors and rounded shapes. Nothing should feel intimidating or corporate. Think 'friendly game' not 'business software'."
            },
            {
                "name": "Gamification First",
                "description": "Incorporate game-like elements: floating decorative icons, celebrations, progress bars, coin/star motifs, and achievement-style badges. Make progress feel rewarding."
            },
            {
                "name": "Large & Touch-Friendly",
                "description": "All interactive elements should be large and easy to tap. Minimum 44px touch targets. Generous padding and spacing throughout."
            },
            {
                "name": "Visual Feedback",
                "description": "Every interaction should have clear feedback: hover states, scale transforms, shadow changes, and animations. Users should always know what's clickable."
            },
            {
                "name": "Encouraging Language",
                "description": "Use positive, empowering copy. Replace 'Submit' with 'Let's Go!', 'Error' with 'Oops, let's try again'. Every message should feel supportive."
            },
            {
                "name": "Delightful Motion",
                "description": "Subtle floating animations, bounce effects, and celebration particles make the interface feel alive and magical."
            }
        ]
    },
    "colorPalette": {
        "primary": {
            "skyBlue": {
                "value": "#60b5f4",
                "usage": "Primary brand color, main CTAs, headers, primary buttons, focus rings"
            },
            "skyBlueLight": {
                "value": "#a8d5f7",
                "usage": "Hover states, secondary buttons, decorative backgrounds, dashed borders"
            },
            "skyBlueDark": {
                "value": "#4a9de0",
                "usage": "Active/pressed states, button hover backgrounds"
            }
        },
        "secondary": {
            "sunshineOrange": {
                "value": "#ffb84d",
                "usage": "Accent color, selected states, highlights, coins, in-progress states"
            },
            "goldenYellow": {
                "value": "#ffc850",
                "usage": "Floating coins, rewards, sparkles, decorative elements"
            },
            "orangeDark": {
                "value": "#ff9d42",
                "usage": "Orange text emphasis, accent text, orange button hover"
            }
        },
        "text": {
            "primary": {
                "value": "#2d5f8d",
                "usage": "Main headings, important text, titles, strong labels"
            },
            "secondary": {
                "value": "#5b9bd5",
                "usage": "Body text, descriptions, subtitles, secondary information"
            },
            "accent": {
                "value": "#ff9d42",
                "usage": "Highlighted text, orange accent text"
            },
            "muted": {
                "value": "#9cabba",
                "usage": "Placeholder text, disabled states, subtle labels, helper text"
            }
        },
        "decorative": {
            "coralPink": {
                "value": "#ffb6c1",
                "usage": "Decorative floating elements, chart color"
            },
            "mintGreen": {
                "value": "#a8e6cf",
                "usage": "Success states, positive feedback, available badges, confirmation"
            },
            "softPurple": {
                "value": "#c9b8e8",
                "usage": "Additional decorative variety in floating elements"
            }
        },
        "backgrounds": {
            "white": {
                "value": "#ffffff",
                "usage": "Card backgrounds, input backgrounds"
            },
            "cream": {
                "value": "#fff9e6",
                "usage": "Warm background areas, gradient endpoints"
            },
            "skyLight": {
                "value": "#f0f8ff",
                "usage": "Main page background, gradient midpoint"
            },
            "skyLighter": {
                "value": "#e8f4fc",
                "usage": "Muted sections, gradient start, secondary button hover"
            },
            "muted": {
                "value": "#f5f8fa",
                "usage": "Subtle background areas"
            }
        },
        "borders": {
            "light": {
                "value": "#e0e9f0",
                "usage": "Default borders, input borders, dividers"
            },
            "focus": {
                "value": "#60b5f4",
                "usage": "Focus state borders"
            },
            "dashed": {
                "value": "#a8d5f7",
                "usage": "Dashed decorative borders on cards"
            }
        },
        "semantic": {
            "success": "#a8e6cf",
            "destructive": "#ff6b6b"
        }
    },
    "gradients": {
        "skyGradient": {
            "css": "linear-gradient(180deg, #e8f4fc 0%, #f0f8ff 50%, #fff9e6 100%)",
            "usage": "Main page background - light blue to cream vertical gradient"
        },
        "skyGradientBlue": {
            "css": "linear-gradient(180deg, #d0e8f7 0%, #e8f4fc 50%, #f0f8ff 100%)",
            "usage": "Alternative page background with more blue"
        },
        "sunsetGradient": {
            "css": "linear-gradient(180deg, #fff9e6 0%, #ffe8cc 50%, #ffd6a8 100%)",
            "usage": "Warm sunset themed sections"
        },
        "cardGradient": {
            "css": "linear-gradient(135deg, #ffffff 0%, #f8fcff 100%)",
            "usage": "Subtle card highlight"
        },
        "buttonGradient": {
            "css": "linear-gradient(135deg, #60b5f4 0%, #4a9de0 100%)",
            "usage": "Primary button backgrounds"
        },
        "orangeGradient": {
            "css": "linear-gradient(135deg, #ffb84d 0%, #ff9d42 100%)",
            "usage": "Orange accent buttons or elements"
        },
        "progressGradient": {
            "css": "linear-gradient(90deg, #60b5f4 0%, #ffb84d 100%)",
            "usage": "Progress bar fills - sky blue to orange"
        },
        "textHero": {
            "css": "linear-gradient(90deg, #60b5f4 0%, #ffb84d 100%)",
            "usage": "Hero text gradient effect (with background-clip: text)"
        }
    },
    "typography": {
        "fontFamily": {
            "primary": {
                "name": "Nunito",
                "fallback": "ui-sans-serif, system-ui, sans-serif",
                "usage": "All text throughout the application. Friendly, rounded letterforms."
            },
            "mono": {
                "name": "Geist Mono",
                "fallback": "ui-monospace, monospace",
                "usage": "Code or numeric displays if needed"
            }
        },
        "fontWeights": {
            "regular": 400,
            "medium": 500,
            "semibold": 600,
            "bold": 700,
            "extrabold": 800
        },
        "scale": {
            "caption": {
                "size": "12px",
                "usage": "Tiny labels, fine print"
            },
            "small": {
                "size": "14px",
                "usage": "Small text, badges, helper text"
            },
            "body": {
                "size": "16px",
                "usage": "Default body text, buttons, inputs"
            },
            "bodyLarge": {
                "size": "18px",
                "usage": "Emphasized body text, subtitles"
            },
            "h2": {
                "size": "24px",
                "usage": "Section headings, card titles"
            },
            "h1": {
                "size": "32px",
                "usage": "Page headings, primary titles"
            },
            "hero": {
                "size": "48px",
                "usage": "Hero text on mobile"
            },
            "heroLarge": {
                "size": "64px",
                "usage": "Hero text on desktop (can go up to 7xl)"
            }
        },
        "guidelines": {
            "headings": "Use extrabold (800) or bold (700) weight. Color: text-primary (#2d5f8d)",
            "body": "Use regular (400) or medium (500) weight. Color: text-secondary (#5b9bd5)",
            "buttons": "Use bold (700) weight. Size: 16px body",
            "labels": "Use semibold (600) weight for labels and badges"
        }
    },
    "spacing": {
        "baseUnit": "8px",
        "scale": {
            "xs": "4px",
            "sm": "8px",
            "md": "16px",
            "lg": "24px",
            "xl": "32px",
            "2xl": "48px",
            "3xl": "64px"
        },
        "componentSpacing": {
            "cardPadding": "24px (lg) to 32px (xl)",
            "buttonPaddingX": "32px",
            "buttonPaddingY": "14px",
            "inputPaddingX": "20px",
            "inputPaddingY": "14px",
            "sectionGap": "32px to 48px",
            "gridGap": "24px",
            "iconGap": "8px"
        }
    },
    "borderRadius": {
        "scale": {
            "sm": "8px",
            "md": "16px",
            "lg": "24px",
            "xl": "32px",
            "full": "9999px"
        },
        "usage": {
            "buttons": "full (9999px) - pill-shaped buttons",
            "cards": "xl (32px) or 3xl - large rounded corners",
            "inputs": "md (16px) - medium rounded",
            "badges": "full (9999px) - pill badges",
            "icons": "lg (24px) or full - decorative icons",
            "selectionCards": "2xl - rounded-2xl (approx 16px)"
        }
    },
    "shadows": {
        "low": {
            "value": "0 2px 8px rgba(45, 95, 141, 0.08)",
            "usage": "Subtle elevation, resting state cards, badges"
        },
        "medium": {
            "value": "0 4px 20px rgba(45, 95, 141, 0.12)",
            "usage": "Standard cards, buttons at rest"
        },
        "high": {
            "value": "0 8px 32px rgba(45, 95, 141, 0.16)",
            "usage": "Elevated cards on hover, modals, popovers"
        },
        "float": {
            "value": "0 6px 24px rgba(96, 181, 244, 0.2)",
            "usage": "Floating decorative elements, floating action buttons"
        },
        "glowBlue": {
            "value": "0 0 20px rgba(96, 181, 244, 0.3)",
            "usage": "Blue focus glow effect"
        },
        "glowOrange": {
            "value": "0 0 20px rgba(255, 184, 77, 0.3)",
            "usage": "Orange/selected state glow effect"
        }
    },
    "animation": {
        "timing": {
            "fast": "150ms",
            "standard": "300ms",
            "slow": "600ms",
            "float": "3000ms"
        },
        "easing": {
            "default": "ease",
            "smooth": "ease-in-out",
            "snappy": "ease-out"
        },
        "keyframeAnimations": {
            "float": {
                "description": "Gentle up-down floating motion",
                "duration": "3s",
                "usage": "Decorative floating elements"
            },
            "floatSlow": {
                "description": "Slower float with subtle rotation",
                "duration": "4s",
                "usage": "Secondary floating elements"
            },
            "floatDrift": {
                "description": "Float with horizontal drift",
                "duration": "5s",
                "usage": "Natural floating variation"
            },
            "bounceGentle": {
                "description": "Gentle bouncing motion",
                "duration": "2s",
                "usage": "Mascot character, attention elements"
            },
            "pulseGlow": {
                "description": "Subtle scale and opacity pulse",
                "duration": "2s",
                "usage": "CTAs needing attention"
            },
            "celebration": {
                "description": "Confetti falling animation",
                "duration": "2.5s",
                "usage": "Success celebrations, wizard completion"
            },
            "fadeUp": {
                "description": "Fade in while moving up",
                "duration": "500ms",
                "usage": "Page/card entrance animations"
            },
            "scaleIn": {
                "description": "Fade in with scale from 0.95",
                "duration": "400ms",
                "usage": "Modal/popover entrance"
            },
            "shake": {
                "description": "Horizontal shake",
                "duration": "500ms",
                "usage": "Error states, validation failures"
            },
            "wiggle": {
                "description": "Rotation wiggle",
                "duration": "500ms",
                "usage": "Attention-grabbing on elements"
            },
            "coinSpin": {
                "description": "3D Y-axis rotation",
                "duration": "2s",
                "usage": "Coin/reward animations"
            },
            "sparkle": {
                "description": "Scale and opacity pulse",
                "duration": "1.5s",
                "usage": "Stars and sparkle effects"
            }
        }
    },
    "components": {
        "card": {
            "adventure": {
                "description": "Standard content card with hover lift effect",
                "styles": {
                    "background": "#ffffff",
                    "borderRadius": "32px (xl) or rounded-3xl",
                    "padding": "24px to 32px",
                    "shadow": "shadow-medium",
                    "hoverTransform": "translateY(-2px)",
                    "hoverShadow": "shadow-high",
                    "transition": "transform 300ms ease, box-shadow 300ms ease"
                }
            },
            "welcome": {
                "description": "Welcome card with dashed border",
                "styles": {
                    "background": "#ffffff or rgba(white, 0.6) with backdrop-blur",
                    "borderRadius": "24px (lg) or rounded-2xl",
                    "padding": "24px",
                    "border": "2-3px dashed #a8d5f7"
                }
            },
            "selection": {
                "description": "Clickable selection card (toggle/choice)",
                "styles": {
                    "background": "#ffffff",
                    "borderRadius": "16px (md) or rounded-2xl",
                    "padding": "16-24px",
                    "border": "3px solid transparent (default), #60b5f4 (hover), #ffb84d (selected)",
                    "selectedBackground": "rgba(255, 184, 77, 0.1)",
                    "selectedScale": "1.05",
                    "selectedShadow": "shadow-glow-orange"
                }
            },
            "step": {
                "description": "Wizard step content card",
                "styles": {
                    "maxWidth": "672px (max-w-2xl)",
                    "background": "#ffffff",
                    "borderRadius": "rounded-3xl (24px+)",
                    "padding": "24px to 32px",
                    "shadow": "shadow-medium",
                    "animation": "fade-in slide-in-from-bottom-4",
                    "centered": true
                }
            },
            "tool": {
                "description": "Tool/feature selection card for dashboard",
                "styles": {
                    "background": "#ffffff",
                    "borderRadius": "rounded-3xl",
                    "padding": "24px",
                    "shadow": "shadow-medium",
                    "hoverScale": "1.02",
                    "hoverShadow": "shadow-high",
                    "iconContainer": {
                        "size": "64px",
                        "borderRadius": "16px (rounded-2xl)",
                        "background": "gradient from sky-blue-light to sky-blue",
                        "shadow": "shadow-low"
                    },
                    "disabledOpacity": "0.6"
                }
            }
        },
        "button": {
            "primary": {
                "description": "Main CTA button - pill shaped",
                "styles": {
                    "display": "inline-flex, centered",
                    "padding": "14px 32px",
                    "fontSize": "16px",
                    "fontWeight": "700 (bold)",
                    "color": "#ffffff",
                    "background": "#60b5f4",
                    "borderRadius": "9999px (full)",
                    "shadow": "shadow-medium",
                    "hoverBackground": "#4a9de0",
                    "hoverScale": "1.02 or 1.05",
                    "hoverShadow": "shadow-high",
                    "activeScale": "0.98",
                    "transition": "all 150ms ease"
                }
            },
            "secondary": {
                "description": "Outlined button",
                "styles": {
                    "padding": "14px 32px",
                    "fontSize": "16px",
                    "fontWeight": "700 (bold)",
                    "color": "#60b5f4",
                    "background": "#ffffff",
                    "border": "2px solid #60b5f4",
                    "borderRadius": "9999px (full)",
                    "hoverBackground": "#f0f8ff"
                }
            },
            "orange": {
                "description": "Orange accent button",
                "styles": {
                    "background": "#ffb84d",
                    "hoverBackground": "#ff9d42"
                }
            },
            "navigation": {
                "description": "Previous/Next wizard navigation buttons",
                "styles": {
                    "previous": {
                        "background": "#ffffff",
                        "border": "2px solid #e0e9f0",
                        "color": "#5b9bd5",
                        "hoverBorderColor": "#60b5f4",
                        "hoverColor": "#60b5f4",
                        "padding": "12px 24px",
                        "borderRadius": "9999px"
                    },
                    "next": {
                        "background": "#60b5f4",
                        "color": "#ffffff",
                        "fontWeight": "bold",
                        "padding": "12px 32px",
                        "borderRadius": "9999px",
                        "disabledBackground": "#9cabba"
                    }
                }
            },
            "floating": {
                "description": "Floating action button (help, etc.)",
                "styles": {
                    "size": "56px (w-14 h-14)",
                    "borderRadius": "50%",
                    "background": "#60b5f4",
                    "color": "#ffffff",
                    "shadow": "shadow-high",
                    "hoverScale": "1.1",
                    "fontSize": "24px"
                }
            }
        },
        "input": {
            "text": {
                "description": "Standard text input",
                "styles": {
                    "width": "100%",
                    "padding": "14px 20px",
                    "fontSize": "16px",
                    "color": "#2d5f8d",
                    "background": "#ffffff",
                    "border": "2px solid #e0e9f0",
                    "borderRadius": "16px (md)",
                    "focusBorderColor": "#60b5f4",
                    "focusShadow": "0 0 0 3px rgba(96, 181, 244, 0.1)",
                    "placeholderColor": "#9cabba"
                }
            },
            "rangeSlider": {
                "description": "Custom range slider",
                "styles": {
                    "trackHeight": "12px",
                    "trackBackground": "muted (#e8f4fc)",
                    "trackBorderRadius": "9999px",
                    "thumbSize": "28px",
                    "thumbBackground": "#ffffff",
                    "thumbBorder": "3px solid #60b5f4",
                    "thumbBorderRadius": "50%",
                    "thumbShadow": "shadow-medium",
                    "thumbHoverScale": "1.1",
                    "thumbHoverBorderColor": "#ffb84d"
                }
            }
        },
        "badge": {
            "description": "Status/label badges - pill shaped",
            "variants": {
                "default": {
                    "background": "#e8f4fc (muted)",
                    "color": "#2d5f8d"
                },
                "blue": {
                    "background": "#a8d5f7",
                    "color": "#2d5f8d"
                },
                "orange": {
                    "background": "rgba(255, 184, 77, 0.2)",
                    "color": "#ff9d42"
                },
                "success": {
                    "background": "rgba(168, 230, 207, 0.3)",
                    "color": "#2d8f6f"
                },
                "state": {
                    "available": "#a8e6cf (mint-green)",
                    "inProgress": "#ffb84d (sunshine-orange)",
                    "usedToday": "#60b5f4 (sky-blue)",
                    "comingSoon": "#9cabba (text-muted)"
                }
            },
            "styles": {
                "display": "inline-flex",
                "padding": "6px 16px",
                "fontSize": "14px",
                "fontWeight": "600 (semibold)",
                "borderRadius": "9999px (full)"
            }
        },
        "progressBar": {
            "description": "Progress indicator with gradient fill",
            "styles": {
                "container": {
                    "width": "100%",
                    "height": "12px (standard) or 8px (compact)",
                    "background": "#e8f4fc (muted)",
                    "borderRadius": "9999px",
                    "overflow": "hidden"
                },
                "fill": {
                    "height": "100%",
                    "background": "linear-gradient(90deg, #60b5f4 0%, #ffb84d 100%)",
                    "borderRadius": "9999px",
                    "transition": "width 500ms ease-out"
                }
            }
        },
        "header": {
            "description": "Page/wizard header",
            "styles": {
                "display": "flex",
                "justifyContent": "space-between",
                "alignItems": "center",
                "padding": "16px to 24px",
                "background": "rgba(255, 255, 255, 0.5) with backdrop-blur-sm",
                "borderBottom": "1px solid #e0e9f0",
                "zIndex": "10"
            },
            "backButton": {
                "background": "#ffffff",
                "borderRadius": "9999px",
                "padding": "8px 16px",
                "shadow": "shadow-low",
                "hoverShadow": "shadow-medium"
            }
        },
        "floatingElements": {
            "description": "Decorative floating icons/shapes for background",
            "guidelines": [
                "Position absolutely with fixed positioning",
                "Use pointer-events-none to not block interactions",
                "Mix of shapes: circles (rounded-full), rounded squares (rounded-xl, rounded-2xl)",
                "Sizes range from 32px to 56px (w-8 to w-14)",
                "Apply float animations with staggered delays",
                "Use decorative colors: golden-yellow, sky-blue-light, coral-pink, mint-green",
                "Include emoji icons inside: 💰, ⭐, 🚀, 👑, 🎁, 🌱, 🤖, 🎯",
                "Large mascot element (96px) positioned bottom-left with bounce animation"
            ]
        },
        "celebration": {
            "description": "Success celebration with falling emoji particles",
            "guidelines": [
                "Trigger on wizard completion or achievements",
                "20 particles falling from top",
                "Emoji variety: ⭐, 🎉, ✨, 🌟, 💰, 🎊, 👑",
                "Random horizontal positions and animation delays",
                "Duration: 2.5 seconds with rotation",
                "Fixed positioning, full screen overlay, pointer-events-none"
            ]
        },
        "tooltip": {
            "description": "Information tooltip on hover",
            "styles": {
                "position": "absolute, above element",
                "padding": "8px 16px",
                "fontSize": "14px",
                "color": "#ffffff",
                "background": "#2d5f8d (text-primary)",
                "borderRadius": "16px (md)",
                "whiteSpace": "nowrap",
                "transition": "opacity 150ms ease"
            }
        },
        "helpBubble": {
            "description": "Fixed help button with expandable info panel",
            "styles": {
                "position": "fixed bottom-6 right-6",
                "zIndex": "50",
                "button": "56px circle, sky-blue background",
                "panel": {
                    "background": "#ffffff",
                    "borderRadius": "rounded-2xl",
                    "shadow": "shadow-high",
                    "padding": "16px",
                    "width": "256px",
                    "animation": "fade-in slide-in-from-bottom-2"
                }
            }
        }
    },
    "layout": {
        "pageStructure": {
            "description": "Standard page layout",
            "elements": [
                "Background: bg-sky-gradient (full page)",
                "FloatingElements: Fixed position decorative layer (z-0)",
                "Header: Sticky top with navigation and branding (z-10)",
                "Main content: Relative positioned, centered (z-10)",
                "HelpBubble: Fixed bottom-right (z-50)"
            ]
        },
        "containerWidths": {
            "full": "100%",
            "prose": "672px (max-w-2xl) - for step content",
            "content": "1152px (max-w-6xl) - for main content areas"
        },
        "gridLayouts": {
            "toolCards": "1 column mobile, 2 columns sm, 3 columns lg, 5 columns xl",
            "selectionGrid": "2-4 columns depending on content"
        },
        "responsiveBreakpoints": {
            "sm": "640px",
            "md": "768px",
            "lg": "1024px",
            "xl": "1280px"
        }
    },
    "wizardPattern": {
        "description": "Multi-step form wizard pattern",
        "structure": {
            "layout": "WizardLayout component wrapping pages",
            "header": "Back button, tool icon + name, language toggle",
            "progressBar": "Below header showing step X / total with percentage",
            "content": "StepCard centered with max-w-2xl",
            "navigation": "WizardNav with Previous/Next buttons at bottom"
        },
        "stepCard": {
            "icon": "Large emoji at top (text-5xl)",
            "title": "Bold heading (text-2xl to text-3xl, extrabold)",
            "subtitle": "Secondary text description",
            "content": "Form fields, selection grids, etc."
        },
        "progressIndicator": {
            "textStyle": "Step X / Y with percentage",
            "barStyle": "Gradient fill from blue to orange"
        },
        "celebrationOnComplete": true
    },
    "iconography": {
        "style": "Lucide icons for UI elements, minimal emoji usage for decorative flair only",
        "lucideIcons": "Use Lucide React as the primary icon library for all UI elements",
        "buttonIcons": {
            "navigation": "ArrowLeft, ArrowRight, ChevronLeft, ChevronRight",
            "actions": "Sparkles (magic/generate), Loader2 (loading), HelpCircle (help), Check (confirm)",
            "tools": "Lightbulb (idea), Package (packaging), Palette (logo), Store (booth), Coins (profit)"
        },
        "decorativeEmoji": {
            "usage": "Use sparingly for celebrations and floating background elements only",
            "allowed": "⭐, ✨ (limit to celebration animations)"
        }
    },
    "accessibility": {
        "focusStyle": {
            "outline": "3px solid #60b5f4",
            "outlineOffset": "2px"
        },
        "selectionStyle": {
            "background": "#a8d5f7",
            "color": "#2d5f8d"
        },
        "minimumTouchTarget": "44px",
        "colorContrast": "Ensure text-primary on white meets WCAG AA"
    },
    "internationalization": {
        "supported": [
            "en",
            "zh"
        ],
        "languageToggle": "LanguageToggle component in header",
        "textDirection": "LTR",
        "useTranslationHook": "useLanguage() from language-provider"
    },
    "techStack": {
        "framework": "Next.js 15 with App Router",
        "styling": "Tailwind CSS v4 with CSS variables",
        "ui": "Shadcn/UI (new-york style)",
        "fonts": "Nunito from Google Fonts",
        "icons": "Lucide React + Emoji",
        "animations": "Custom CSS keyframes + tw-animate-css"
    },
    "aiInstructions": {
        "summary": "When building UI for this app, create a fun, game-like experience for children. Every element should feel playful and encouraging.",
        "dos": [
            "Use the sky gradient background (bg-sky-gradient) for pages",
            "Include FloatingElements component for visual interest",
            "Use large, rounded cards (rounded-3xl) with generous padding",
            "Apply pill-shaped buttons (rounded-full) for CTAs",
            "Add hover scale transforms and shadow transitions",
            "Use emoji icons generously for visual appeal",
            "Apply float and bounce animations to decorative elements",
            "Use the blue-to-orange gradient for progress indicators",
            "Include HelpBubble for contextual assistance",
            "Celebrate successes with the Celebration component"
        ],
        "donts": [
            "Don't use sharp corners - everything should be rounded",
            "Don't use plain gray backgrounds - use the sky gradient or white",
            "Don't use small, hard-to-tap buttons",
            "Don't use formal or technical language",
            "Don't make anything feel 'corporate' or intimidating",
            "Don't use static layouts - add subtle animations",
            "Don't forget visual feedback on interactive elements"
        ],
        "colorPriorities": [
            "Primary actions: sky-blue (#60b5f4)",
            "Selected/active states: sunshine-orange (#ffb84d)",
            "Text: text-primary (#2d5f8d) for headings, text-secondary (#5b9bd5) for body",
            "Success: mint-green (#a8e6cf)",
            "Backgrounds: white cards on sky-gradient background"
        ]
    }
}